driftdb/__init__.py
driftdb/cli.py
driftdb/entrypoint.py
driftdb/logger.py
driftdb/server.py
driftdb/user_defined_function.py
driftdb/version.py
driftdb/alerting/__init__.py
driftdb/alerting/dry_run_alert_handler.py
driftdb/alerting/handlers.py
driftdb/alerting/helpers.py
driftdb/alerting/interface.py
driftdb/alerting/summarize_dataframe_updates.py
driftdb/alerting/transport/__init__.py
driftdb/alerting/transport/console.py
driftdb/alerting/transport/github.py
driftdb/alerting/transport/gitlab.py
driftdb/alerting/transport/interface.py
driftdb/bin/datadrift-linux
driftdb/bin/datadrift-mac-intel
driftdb/bin/datadrift-mac-m1
driftdb/bin/frontend/dist/github-mark.svg
driftdb/bin/frontend/dist/index.html
driftdb/bin/frontend/dist/logo.png
driftdb/bin/frontend/dist/assets/buttons.esm-48f94bc9.js
driftdb/bin/frontend/dist/assets/index-38ed970c.css
driftdb/bin/frontend/dist/assets/index-ddae8513.js
driftdb/cli/__init__.py
driftdb/cli/common.py
driftdb/cli/dbt.py
driftdb/cli/seed.py
driftdb/cli/server.py
driftdb/cli/snapshot.py
driftdb/cli/store.py
driftdb/connectors/__init__.py
driftdb/connectors/abstract_connector.py
driftdb/connectors/common.py
driftdb/connectors/github_connector.py
driftdb/connectors/local_connector.py
driftdb/connectors/workflow.py
driftdb/dataframe/__init__.py
driftdb/dataframe/dataframe_update_breakdown.py
driftdb/dataframe/detect_outliers.py
driftdb/dataframe/helpers.py
driftdb/dataframe/seed.py
driftdb/dataframe/summarize_dataframe_updates.py
driftdb/dbt/__init__.py
driftdb/dbt/snapshot.py
driftdb/dbt/snapshot_to_drift.py
driftdb/drift_evaluator/__init__.py
driftdb/drift_evaluator/drift_evaluators.py
driftdb/drift_evaluator/drift_evaluators_dry_run.py
driftdb/drift_evaluator/interface.py
driftdb/query_builder/__init__.py
driftdb/query_builder/query_builder.py
tests/__init__.py
tests/test_compare_dataframes.py
tests/test_convert_snapshot_diff_to_drift_summary.py
tests/test_dataframe_update_breakdown.py
driftdb-0.1.4.dist-info/METADATA
driftdb-0.1.4.dist-info/WHEEL
driftdb-0.1.4.dist-info/entry_points.txt
driftdb-0.1.4.dist-info/top_level.txt
driftdb-0.1.4.dist-info/RECORD
