Metadata-Version: 2.1
Name: driftdb
Version: 0.1.4
Summary: Historical metric store
Home-page: https://github.com/data-drift/data-drift/tree/main/tools/driftdb
Author: Sammy Teillet
Author-email: sammy.teillet@gmail.com
Classifier: Programming Language :: Python :: 3
Classifier: License :: OSI Approved :: MIT License
Classifier: Operating System :: OS Independent
Requires-Python: >=3.6
Requires-Dist: black
Requires-Dist: click
Requires-Dist: dbt-core
Requires-Dist: Faker
Requires-Dist: GitPython
Requires-Dist: inquirer
Requires-Dist: isort
Requires-Dist: pandas
Requires-Dist: pandas-stubs
Requires-Dist: PyGithub
Requires-Dist: python-gitlab
Requires-Dist: tabulate
Requires-Dist: typer[all]
Requires-Dist: typing-extensions ==4.7.1
